offspot_runtime/__init__.py
offspot_runtime/ap.py
offspot_runtime/checks.py
offspot_runtime/configlib.py
offspot_runtime/containers.py
offspot_runtime/dnsmasqspoof.py
offspot_runtime/ethernet.py
offspot_runtime/fromfile.py
offspot_runtime/hostname.py
offspot_runtime/timezone.py
offspot_runtime_config-1.2.0.dist-info/LICENSE
offspot_runtime_config-1.2.0.dist-info/METADATA
offspot_runtime_config-1.2.0.dist-info/WHEEL
offspot_runtime_config-1.2.0.dist-info/entry_points.txt
offspot_runtime_config-1.2.0.dist-info/top_level.txt
offspot_runtime_config-1.2.0.dist-info/RECORD
