Metadata-Version: 2.1
Name: offspot-runtime-config
Version: 1.2.0
Summary: Offspot Runtime Configuration Scripts & Library
Home-page: https://github.com/offspot/runtime-config
Author: kiwix
Author-email: reg@kiwix.org
License: GPLv3+
Keywords: offspot
Classifier: Development Status :: 4 - Beta
Classifier: Intended Audience :: Developers
Classifier: Programming Language :: Python
Classifier: Programming Language :: Python :: 3.9
Classifier: Programming Language :: Python :: 3.10
Classifier: Programming Language :: Python :: 3.11
Classifier: License :: OSI Approved :: GNU General Public License v3 or later (GPLv3+)
Requires-Python: >=3.9
License-File: LICENSE
Requires-Dist: PyYaml (<7.0,>=5.3)
Requires-Dist: tzdata (>=2022.7)
Requires-Dist: iso3166 (>=2.1.1)
